volcano/twistedclient/__init__.py
volcano/twistedclient/twisted_client_mt.py
volcano/twistedclient/twisted_client_st.py
volcano/twistedclient/twisted_factory.py
volcano_twistedclient-0.2.6.dist-info/LICENSE
volcano_twistedclient-0.2.6.dist-info/METADATA
volcano_twistedclient-0.2.6.dist-info/WHEEL
volcano_twistedclient-0.2.6.dist-info/top_level.txt
volcano_twistedclient-0.2.6.dist-info/RECORD
